{"app":{"default_permission":{"identifier":"default","description":"Default permissions for the plugin.","permissions":["allow-version","allow-name","allow-tauri-version"]},"permissions":{"allow-app-hide":{"version":null,"identifier":"allow-app-hide","description":"Enables the app_hide command without any pre-configured scope.","commands":{"allow":["app_hide"],"deny":[]},"scope":{}},"allow-app-show":{"version":null,"identifier":"allow-app-show","description":"Enables the app_show command without any pre-configured scope.","commands":{"allow":["app_show"],"deny":[]},"scope":{}},"allow-name":{"version":null,"identifier":"allow-name","description":"Enables the name command without any pre-configured scope.","commands":{"allow":["name"],"deny":[]},"scope":{}},"allow-tauri-version":{"version":null,"identifier":"allow-tauri-version","description":"Enables the tauri_version command without any pre-configured scope.","commands":{"allow":["tauri_version"],"deny":[]},"scope":{}},"allow-version":{"version":null,"identifier":"allow-version","description":"Enables the version command without any pre-configured scope.","commands":{"allow":["version"],"deny":[]},"scope":{}},"deny-app-hide":{"version":null,"identifier":"deny-app-hide","description":"Denies the app_hide command without any pre-configured scope.","commands":{"allow":[],"deny":["app_hide"]},"scope":{}},"deny-app-show":{"version":null,"identifier":"deny-app-show","description":"Denies the app_show command without any pre-configured scope.","commands":{"allow":[],"deny":["app_show"]},"scope":{}},"deny-name":{"version":null,"identifier":"deny-name","description":"Denies the name command without any pre-configured scope.","commands":{"allow":[],"deny":["name"]},"scope":{}},"deny-tauri-version":{"version":null,"identifier":"deny-tauri-version","description":"Denies the tauri_version command without any pre-configured scope.","commands":{"allow":[],"deny":["tauri_version"]},"scope":{}},"deny-version":{"version":null,"identifier":"deny-version","description":"Denies the version command without any pre-configured scope.","commands":{"allow":[],"deny":["version"]},"scope":{}}},"permission_sets":{},"global_scope_schema":null},"event":{"default_permission":{"identifier":"default","description":"Default permissions for the plugin.","permissions":["allow-listen","allow-unlisten","allow-emit","allow-emit-to"]},"permissions":{"allow-emit":{"version":null,"identifier":"allow-emit","description":"Enables the emit command without any pre-configured scope.","commands":{"allow":["emit"],"deny":[]},"scope":{}},"allow-emit-to":{"version":null,"identifier":"allow-emit-to","description":"Enables the emit_to command without any pre-configured scope.","commands":{"allow":["emit_to"],"deny":[]},"scope":{}},"allow-listen":{"version":null,"identifier":"allow-listen","description":"Enables the listen command without any pre-configured scope.","commands":{"allow":["listen"],"deny":[]},"scope":{}},"allow-unlisten":{"version":null,"identifier":"allow-unlisten","description":"Enables the unlisten command without any pre-configured scope.","commands":{"allow":["unlisten"],"deny":[]},"scope":{}},"deny-emit":{"version":null,"identifier":"deny-emit","description":"Denies the emit command without any pre-configured scope.","commands":{"allow":[],"deny":["emit"]},"scope":{}},"deny-emit-to":{"version":null,"identifier":"deny-emit-to","description":"Denies the emit_to command without any pre-configured scope.","commands":{"allow":[],"deny":["emit_to"]},"scope":{}},"deny-listen":{"version":null,"identifier":"deny-listen","description":"Denies the listen command without any pre-configured scope.","commands":{"allow":[],"deny":["listen"]},"scope":{}},"deny-unlisten":{"version":null,"identifier":"deny-unlisten","description":"Denies the unlisten command without any pre-configured scope.","commands":{"allow":[],"deny":["unlisten"]},"scope":{}}},"permission_sets":{},"global_scope_schema":null},"menu":{"default_permission":{"identifier":"default","description":"Default permissions for the plugin.","permissions":[]},"permissions":{"allow-append":{"version":null,"identifier":"allow-append","description":"Enables the append command without any pre-configured scope.","commands":{"allow":["append"],"deny":[]},"scope":{}},"allow-create-default":{"version":null,"identifier":"allow-create-default","description":"Enables the create_default command without any pre-configured scope.","commands":{"allow":["create_default"],"deny":[]},"scope":{}},"allow-get":{"version":null,"identifier":"allow-get","description":"Enables the get command without any pre-configured scope.","commands":{"allow":["get"],"deny":[]},"scope":{}},"allow-insert":{"version":null,"identifier":"allow-insert","description":"Enables the insert command without any pre-configured scope.","commands":{"allow":["insert"],"deny":[]},"scope":{}},"allow-is-checked":{"version":null,"identifier":"allow-is-checked","description":"Enables the is_checked command without any pre-configured scope.","commands":{"allow":["is_checked"],"deny":[]},"scope":{}},"allow-is-enabled":{"version":null,"identifier":"allow-is-enabled","description":"Enables the is_enabled command without any pre-configured scope.","commands":{"allow":["is_enabled"],"deny":[]},"scope":{}},"allow-items":{"version":null,"identifier":"allow-items","description":"Enables the items command without any pre-configured scope.","commands":{"allow":["items"],"deny":[]},"scope":{}},"allow-new":{"version":null,"identifier":"allow-new","description":"Enables the new command without any pre-configured scope.","commands":{"allow":["new"],"deny":[]},"scope":{}},"allow-popup":{"version":null,"identifier":"allow-popup","description":"Enables the popup command without any pre-configured scope.","commands":{"allow":["popup"],"deny":[]},"scope":{}},"allow-prepend":{"version":null,"identifier":"allow-prepend","description":"Enables the prepend command without any pre-configured scope.","commands":{"allow":["prepend"],"deny":[]},"scope":{}},"allow-remove":{"version":null,"identifier":"allow-remove","description":"Enables the remove command without any pre-configured scope.","commands":{"allow":["remove"],"deny":[]},"scope":{}},"allow-remove-at":{"version":null,"identifier":"allow-remove-at","description":"Enables the remove_at command without any pre-configured scope.","commands":{"allow":["remove_at"],"deny":[]},"scope":{}},"allow-set-accelerator":{"version":null,"identifier":"allow-set-accelerator","description":"Enables the set_accelerator command without any pre-configured scope.","commands":{"allow":["set_accelerator"],"deny":[]},"scope":{}},"allow-set-as-app-menu":{"version":null,"identifier":"allow-set-as-app-menu","description":"Enables the set_as_app_menu command without any pre-configured scope.","commands":{"allow":["set_as_app_menu"],"deny":[]},"scope":{}},"allow-set-as-help-menu-for-nsapp":{"version":null,"identifier":"allow-set-as-help-menu-for-nsapp","description":"Enables the set_as_help_menu_for_nsapp command without any pre-configured scope.","commands":{"allow":["set_as_help_menu_for_nsapp"],"deny":[]},"scope":{}},"allow-set-as-window-menu":{"version":null,"identifier":"allow-set-as-window-menu","description":"Enables the set_as_window_menu command without any pre-configured scope.","commands":{"allow":["set_as_window_menu"],"deny":[]},"scope":{}},"allow-set-as-windows-menu-for-nsapp":{"version":null,"identifier":"allow-set-as-windows-menu-for-nsapp","description":"Enables the set_as_windows_menu_for_nsapp command without any pre-configured scope.","commands":{"allow":["set_as_windows_menu_for_nsapp"],"deny":[]},"scope":{}},"allow-set-checked":{"version":null,"identifier":"allow-set-checked","description":"Enables the set_checked command without any pre-configured scope.","commands":{"allow":["set_checked"],"deny":[]},"scope":{}},"allow-set-enabled":{"version":null,"identifier":"allow-set-enabled","description":"Enables the set_enabled command without any pre-configured scope.","commands":{"allow":["set_enabled"],"deny":[]},"scope":{}},"allow-set-icon":{"version":null,"identifier":"allow-set-icon","description":"Enables the set_icon command without any pre-configured scope.","commands":{"allow":["set_icon"],"deny":[]},"scope":{}},"allow-set-text":{"version":null,"identifier":"allow-set-text","description":"Enables the set_text command without any pre-configured scope.","commands":{"allow":["set_text"],"deny":[]},"scope":{}},"allow-text":{"version":null,"identifier":"allow-text","description":"Enables the text command without any pre-configured scope.","commands":{"allow":["text"],"deny":[]},"scope":{}},"deny-append":{"version":null,"identifier":"deny-append","description":"Denies the append command without any pre-configured scope.","commands":{"allow":[],"deny":["append"]},"scope":{}},"deny-create-default":{"version":null,"identifier":"deny-create-default","description":"Denies the create_default command without any pre-configured scope.","commands":{"allow":[],"deny":["create_default"]},"scope":{}},"deny-get":{"version":null,"identifier":"deny-get","description":"Denies the get command without any pre-configured scope.","commands":{"allow":[],"deny":["get"]},"scope":{}},"deny-insert":{"version":null,"identifier":"deny-insert","description":"Denies the insert command without any pre-configured scope.","commands":{"allow":[],"deny":["insert"]},"scope":{}},"deny-is-checked":{"version":null,"identifier":"deny-is-checked","description":"Denies the is_checked command without any pre-configured scope.","commands":{"allow":[],"deny":["is_checked"]},"scope":{}},"deny-is-enabled":{"version":null,"identifier":"deny-is-enabled","description":"Denies the is_enabled command without any pre-configured scope.","commands":{"allow":[],"deny":["is_enabled"]},"scope":{}},"deny-items":{"version":null,"identifier":"deny-items","description":"Denies the items command without any pre-configured scope.","commands":{"allow":[],"deny":["items"]},"scope":{}},"deny-new":{"version":null,"identifier":"deny-new","description":"Denies the new command without any pre-configured scope.","commands":{"allow":[],"deny":["new"]},"scope":{}},"deny-popup":{"version":null,"identifier":"deny-popup","description":"Denies the popup command without any pre-configured scope.","commands":{"allow":[],"deny":["popup"]},"scope":{}},"deny-prepend":{"version":null,"identifier":"deny-prepend","description":"Denies the prepend command without any pre-configured scope.","commands":{"allow":[],"deny":["prepend"]},"scope":{}},"deny-remove":{"version":null,"identifier":"deny-remove","description":"Denies the remove command without any pre-configured scope.","commands":{"allow":[],"deny":["remove"]},"scope":{}},"deny-remove-at":{"version":null,"identifier":"deny-remove-at","description":"Denies the remove_at command without any pre-configured scope.","commands":{"allow":[],"deny":["remove_at"]},"scope":{}},"deny-set-accelerator":{"version":null,"identifier":"deny-set-accelerator","description":"Denies the set_accelerator command without any pre-configured scope.","commands":{"allow":[],"deny":["set_accelerator"]},"scope":{}},"deny-set-as-app-menu":{"version":null,"identifier":"deny-set-as-app-menu","description":"Denies the set_as_app_menu command without any pre-configured scope.","commands":{"allow":[],"deny":["set_as_app_menu"]},"scope":{}},"deny-set-as-help-menu-for-nsapp":{"version":null,"identifier":"deny-set-as-help-menu-for-nsapp","description":"Denies the set_as_help_menu_for_nsapp command without any pre-configured scope.","commands":{"allow":[],"deny":["set_as_help_menu_for_nsapp"]},"scope":{}},"deny-set-as-window-menu":{"version":null,"identifier":"deny-set-as-window-menu","description":"Denies the set_as_window_menu command without any pre-configured scope.","commands":{"allow":[],"deny":["set_as_window_menu"]},"scope":{}},"deny-set-as-windows-menu-for-nsapp":{"version":null,"identifier":"deny-set-as-windows-menu-for-nsapp","description":"Denies the set_as_windows_menu_for_nsapp command without any pre-configured scope.","commands":{"allow":[],"deny":["set_as_windows_menu_for_nsapp"]},"scope":{}},"deny-set-checked":{"version":null,"identifier":"deny-set-checked","description":"Denies the set_checked command without any pre-configured scope.","commands":{"allow":[],"deny":["set_checked"]},"scope":{}},"deny-set-enabled":{"version":null,"identifier":"deny-set-enabled","description":"Denies the set_enabled command without any pre-configured scope.","commands":{"allow":[],"deny":["set_enabled"]},"scope":{}},"deny-set-icon":{"version":null,"identifier":"deny-set-icon","description":"Denies the set_icon command without any pre-configured scope.","commands":{"allow":[],"deny":["set_icon"]},"scope":{}},"deny-set-text":{"version":null,"identifier":"deny-set-text","description":"Denies the set_text command without any pre-configured scope.","commands":{"allow":[],"deny":["set_text"]},"scope":{}},"deny-text":{"version":null,"identifier":"deny-text","description":"Denies the text command without any pre-configured scope.","commands":{"allow":[],"deny":["text"]},"scope":{}}},"permission_sets":{},"global_scope_schema":null},"path":{"default_permission":{"identifier":"default","description":"Default permissions for the plugin.","permissions":["allow-resolve-directory","allow-resolve","allow-normalize","allow-join","allow-dirname","allow-extname","allow-basename","allow-is-absolute"]},"permissions":{"allow-basename":{"version":null,"identifier":"allow-basename","description":"Enables the basename command without any pre-configured scope.","commands":{"allow":["basename"],"deny":[]},"scope":{}},"allow-dirname":{"version":null,"identifier":"allow-dirname","description":"Enables the dirname command without any pre-configured scope.","commands":{"allow":["dirname"],"deny":[]},"scope":{}},"allow-extname":{"version":null,"identifier":"allow-extname","description":"Enables the extname command without any pre-configured scope.","commands":{"allow":["extname"],"deny":[]},"scope":{}},"allow-is-absolute":{"version":null,"identifier":"allow-is-absolute","description":"Enables the is_absolute command without any pre-configured scope.","commands":{"allow":["is_absolute"],"deny":[]},"scope":{}},"allow-join":{"version":null,"identifier":"allow-join","description":"Enables the join command without any pre-configured scope.","commands":{"allow":["join"],"deny":[]},"scope":{}},"allow-normalize":{"version":null,"identifier":"allow-normalize","description":"Enables the normalize command without any pre-configured scope.","commands":{"allow":["normalize"],"deny":[]},"scope":{}},"allow-resolve":{"version":null,"identifier":"allow-resolve","description":"Enables the resolve command without any pre-configured scope.","commands":{"allow":["resolve"],"deny":[]},"scope":{}},"allow-resolve-directory":{"version":null,"identifier":"allow-resolve-directory","description":"Enables the resolve_directory command without any pre-configured scope.","commands":{"allow":["resolve_directory"],"deny":[]},"scope":{}},"deny-basename":{"version":null,"identifier":"deny-basename","description":"Denies the basename command without any pre-configured scope.","commands":{"allow":[],"deny":["basename"]},"scope":{}},"deny-dirname":{"version":null,"identifier":"deny-dirname","description":"Denies the dirname command without any pre-configured scope.","commands":{"allow":[],"deny":["dirname"]},"scope":{}},"deny-extname":{"version":null,"identifier":"deny-extname","description":"Denies the extname command without any pre-configured scope.","commands":{"allow":[],"deny":["extname"]},"scope":{}},"deny-is-absolute":{"version":null,"identifier":"deny-is-absolute","description":"Denies the is_absolute command without any pre-configured scope.","commands":{"allow":[],"deny":["is_absolute"]},"scope":{}},"deny-join":{"version":null,"identifier":"deny-join","description":"Denies the join command without any pre-configured scope.","commands":{"allow":[],"deny":["join"]},"scope":{}},"deny-normalize":{"version":null,"identifier":"deny-normalize","description":"Denies the normalize command without any pre-configured scope.","commands":{"allow":[],"deny":["normalize"]},"scope":{}},"deny-resolve":{"version":null,"identifier":"deny-resolve","description":"Denies the resolve command without any pre-configured scope.","commands":{"allow":[],"deny":["resolve"]},"scope":{}},"deny-resolve-directory":{"version":null,"identifier":"deny-resolve-directory","description":"Denies the resolve_directory command without any pre-configured scope.","commands":{"allow":[],"deny":["resolve_directory"]},"scope":{}}},"permission_sets":{},"global_scope_schema":null},"resources":{"default_permission":{"identifier":"default","description":"Default permissions for the plugin.","permissions":["allow-close"]},"permissions":{"allow-close":{"version":null,"identifier":"allow-close","description":"Enables the close command without any pre-configured scope.","commands":{"allow":["close"],"deny":[]},"scope":{}},"deny-close":{"version":null,"identifier":"deny-close","description":"Denies the close command without any pre-configured scope.","commands":{"allow":[],"deny":["close"]},"scope":{}}},"permission_sets":{},"global_scope_schema":null},"shell":{"default_permission":null,"permissions":{"allow-execute":{"version":null,"identifier":"allow-execute","description":"Enables the execute command without any pre-configured scope.","commands":{"allow":["execute"],"deny":[]},"scope":{}},"allow-kill":{"version":null,"identifier":"allow-kill","description":"Enables the kill command without any pre-configured scope.","commands":{"allow":["kill"],"deny":[]},"scope":{}},"allow-open":{"version":null,"identifier":"allow-open","description":"Enables the open command without any pre-configured scope.","commands":{"allow":["open"],"deny":[]},"scope":{}},"allow-stdin-write":{"version":null,"identifier":"allow-stdin-write","description":"Enables the stdin_write command without any pre-configured scope.","commands":{"allow":["stdin_write"],"deny":[]},"scope":{}},"deny-execute":{"version":null,"identifier":"deny-execute","description":"Denies the execute command without any pre-configured scope.","commands":{"allow":[],"deny":["execute"]},"scope":{}},"deny-kill":{"version":null,"identifier":"deny-kill","description":"Denies the kill command without any pre-configured scope.","commands":{"allow":[],"deny":["kill"]},"scope":{}},"deny-open":{"version":null,"identifier":"deny-open","description":"Denies the open command without any pre-configured scope.","commands":{"allow":[],"deny":["open"]},"scope":{}},"deny-stdin-write":{"version":null,"identifier":"deny-stdin-write","description":"Denies the stdin_write command without any pre-configured scope.","commands":{"allow":[],"deny":["stdin_write"]},"scope":{}}},"permission_sets":{},"global_scope_schema":{"$schema":"http://json-schema.org/draft-07/schema#","definitions":{"ShellAllowedArg":{"anyOf":[{"description":"A non-configurable argument that is passed to the command in the order it was specified.","type":"string"},{"additionalProperties":false,"description":"A variable that is set while calling the command from the webview API.","properties":{"validator":{"description":"[regex] validator to require passed values to conform to an expected input.\n\nThis will require the argument value passed to this variable to match the `validator` regex before it will be executed.\n\n[regex]: https://docs.rs/regex/latest/regex/#syntax","type":"string"}},"required":["validator"],"type":"object"}],"description":"A command argument allowed to be executed by the webview API."},"ShellAllowedArgs":{"anyOf":[{"description":"Use a simple boolean to allow all or disable all arguments to this command configuration.","type":"boolean"},{"description":"A specific set of [`ShellAllowedArg`] that are valid to call for the command configuration.","items":{"$ref":"#/definitions/ShellAllowedArg"},"type":"array"}],"description":"A set of command arguments allowed to be executed by the webview API.\n\nA value of `true` will allow any arguments to be passed to the command. `false` will disable all arguments. A list of [`ShellAllowedArg`] will set those arguments as the only valid arguments to be passed to the attached command configuration."}},"description":"A command allowed to be executed by the webview API.","properties":{"args":{"allOf":[{"$ref":"#/definitions/ShellAllowedArgs"}],"description":"The allowed arguments for the command execution."},"command":{"description":"The command name. It can start with a variable that resolves to a system base directory. The variables are: `$AUDIO`, `$CACHE`, `$CONFIG`, `$DATA`, `$LOCALDATA`, `$DESKTOP`, `$DOCUMENT`, `$DOWNLOAD`, `$EXE`, `$FONT`, `$HOME`, `$PICTURE`, `$PUBLIC`, `$RUNTIME`, `$TEMPLATE`, `$VIDEO`, `$RESOURCE`, `$APP`, `$LOG`, `$TEMP`, `$APPCONFIG`, `$APPDATA`, `$APPLOCALDATA`, `$APPCACHE`, `$APPLOG`.","type":"string"},"name":{"description":"The name for this allowed shell command configuration.\n\nThis name will be used inside of the webview API to call this command along with any specified arguments.","type":"string"},"sidecar":{"description":"If this command is a sidecar command.","type":"boolean"}},"required":["args","command","name","sidecar"],"title":"Entry","type":"object"}},"sql":{"default_permission":null,"permissions":{"allow-close":{"version":null,"identifier":"allow-close","description":"Enables the close command without any pre-configured scope.","commands":{"allow":["close"],"deny":[]},"scope":{}},"allow-execute":{"version":null,"identifier":"allow-execute","description":"Enables the execute command without any pre-configured scope.","commands":{"allow":["execute"],"deny":[]},"scope":{}},"allow-load":{"version":null,"identifier":"allow-load","description":"Enables the load command without any pre-configured scope.","commands":{"allow":["load"],"deny":[]},"scope":{}},"allow-select":{"version":null,"identifier":"allow-select","description":"Enables the select command without any pre-configured scope.","commands":{"allow":["select"],"deny":[]},"scope":{}},"deny-close":{"version":null,"identifier":"deny-close","description":"Denies the close command without any pre-configured scope.","commands":{"allow":[],"deny":["close"]},"scope":{}},"deny-execute":{"version":null,"identifier":"deny-execute","description":"Denies the execute command without any pre-configured scope.","commands":{"allow":[],"deny":["execute"]},"scope":{}},"deny-load":{"version":null,"identifier":"deny-load","description":"Denies the load command without any pre-configured scope.","commands":{"allow":[],"deny":["load"]},"scope":{}},"deny-select":{"version":null,"identifier":"deny-select","description":"Denies the select command without any pre-configured scope.","commands":{"allow":[],"deny":["select"]},"scope":{}}},"permission_sets":{},"global_scope_schema":null},"tray":{"default_permission":{"identifier":"default","description":"Default permissions for the plugin.","permissions":[]},"permissions":{"allow-new":{"version":null,"identifier":"allow-new","description":"Enables the new command without any pre-configured scope.","commands":{"allow":["new"],"deny":[]},"scope":{}},"allow-set-icon":{"version":null,"identifier":"allow-set-icon","description":"Enables the set_icon command without any pre-configured scope.","commands":{"allow":["set_icon"],"deny":[]},"scope":{}},"allow-set-icon-as-template":{"version":null,"identifier":"allow-set-icon-as-template","description":"Enables the set_icon_as_template command without any pre-configured scope.","commands":{"allow":["set_icon_as_template"],"deny":[]},"scope":{}},"allow-set-menu":{"version":null,"identifier":"allow-set-menu","description":"Enables the set_menu command without any pre-configured scope.","commands":{"allow":["set_menu"],"deny":[]},"scope":{}},"allow-set-show-menu-on-left-click":{"version":null,"identifier":"allow-set-show-menu-on-left-click","description":"Enables the set_show_menu_on_left_click command without any pre-configured scope.","commands":{"allow":["set_show_menu_on_left_click"],"deny":[]},"scope":{}},"allow-set-temp-dir-path":{"version":null,"identifier":"allow-set-temp-dir-path","description":"Enables the set_temp_dir_path command without any pre-configured scope.","commands":{"allow":["set_temp_dir_path"],"deny":[]},"scope":{}},"allow-set-title":{"version":null,"identifier":"allow-set-title","description":"Enables the set_title command without any pre-configured scope.","commands":{"allow":["set_title"],"deny":[]},"scope":{}},"allow-set-tooltip":{"version":null,"identifier":"allow-set-tooltip","description":"Enables the set_tooltip command without any pre-configured scope.","commands":{"allow":["set_tooltip"],"deny":[]},"scope":{}},"allow-set-visible":{"version":null,"identifier":"allow-set-visible","description":"Enables the set_visible command without any pre-configured scope.","commands":{"allow":["set_visible"],"deny":[]},"scope":{}},"deny-new":{"version":null,"identifier":"deny-new","description":"Denies the new command without any pre-configured scope.","commands":{"allow":[],"deny":["new"]},"scope":{}},"deny-set-icon":{"version":null,"identifier":"deny-set-icon","description":"Denies the set_icon command without any pre-configured scope.","commands":{"allow":[],"deny":["set_icon"]},"scope":{}},"deny-set-icon-as-template":{"version":null,"identifier":"deny-set-icon-as-template","description":"Denies the set_icon_as_template command without any pre-configured scope.","commands":{"allow":[],"deny":["set_icon_as_template"]},"scope":{}},"deny-set-menu":{"version":null,"identifier":"deny-set-menu","description":"Denies the set_menu command without any pre-configured scope.","commands":{"allow":[],"deny":["set_menu"]},"scope":{}},"deny-set-show-menu-on-left-click":{"version":null,"identifier":"deny-set-show-menu-on-left-click","description":"Denies the set_show_menu_on_left_click command without any pre-configured scope.","commands":{"allow":[],"deny":["set_show_menu_on_left_click"]},"scope":{}},"deny-set-temp-dir-path":{"version":null,"identifier":"deny-set-temp-dir-path","description":"Denies the set_temp_dir_path command without any pre-configured scope.","commands":{"allow":[],"deny":["set_temp_dir_path"]},"scope":{}},"deny-set-title":{"version":null,"identifier":"deny-set-title","description":"Denies the set_title command without any pre-configured scope.","commands":{"allow":[],"deny":["set_title"]},"scope":{}},"deny-set-tooltip":{"version":null,"identifier":"deny-set-tooltip","description":"Denies the set_tooltip command without any pre-configured scope.","commands":{"allow":[],"deny":["set_tooltip"]},"scope":{}},"deny-set-visible":{"version":null,"identifier":"deny-set-visible","description":"Denies the set_visible command without any pre-configured scope.","commands":{"allow":[],"deny":["set_visible"]},"scope":{}}},"permission_sets":{},"global_scope_schema":null},"webview":{"default_permission":{"identifier":"default","description":"Default permissions for the plugin.","permissions":["allow-webview-position","allow-webview-size","allow-internal-toggle-devtools"]},"permissions":{"allow-create-webview":{"version":null,"identifier":"allow-create-webview","description":"Enables the create_webview command without any pre-configured scope.","commands":{"allow":["create_webview"],"deny":[]},"scope":{}},"allow-create-webview-window":{"version":null,"identifier":"allow-create-webview-window","description":"Enables the create_webview_window command without any pre-configured scope.","commands":{"allow":["create_webview_window"],"deny":[]},"scope":{}},"allow-internal-toggle-devtools":{"version":null,"identifier":"allow-internal-toggle-devtools","description":"Enables the internal_toggle_devtools command without any pre-configured scope.","commands":{"allow":["internal_toggle_devtools"],"deny":[]},"scope":{}},"allow-print":{"version":null,"identifier":"allow-print","description":"Enables the print command without any pre-configured scope.","commands":{"allow":["print"],"deny":[]},"scope":{}},"allow-set-webview-focus":{"version":null,"identifier":"allow-set-webview-focus","description":"Enables the set_webview_focus command without any pre-configured scope.","commands":{"allow":["set_webview_focus"],"deny":[]},"scope":{}},"allow-set-webview-position":{"version":null,"identifier":"allow-set-webview-position","description":"Enables the set_webview_position command without any pre-configured scope.","commands":{"allow":["set_webview_position"],"deny":[]},"scope":{}},"allow-set-webview-size":{"version":null,"identifier":"allow-set-webview-size","description":"Enables the set_webview_size command without any pre-configured scope.","commands":{"allow":["set_webview_size"],"deny":[]},"scope":{}},"allow-webview-close":{"version":null,"identifier":"allow-webview-close","description":"Enables the webview_close command without any pre-configured scope.","commands":{"allow":["webview_close"],"deny":[]},"scope":{}},"allow-webview-position":{"version":null,"identifier":"allow-webview-position","description":"Enables the webview_position command without any pre-configured scope.","commands":{"allow":["webview_position"],"deny":[]},"scope":{}},"allow-webview-size":{"version":null,"identifier":"allow-webview-size","description":"Enables the webview_size command without any pre-configured scope.","commands":{"allow":["webview_size"],"deny":[]},"scope":{}},"deny-create-webview":{"version":null,"identifier":"deny-create-webview","description":"Denies the create_webview command without any pre-configured scope.","commands":{"allow":[],"deny":["create_webview"]},"scope":{}},"deny-create-webview-window":{"version":null,"identifier":"deny-create-webview-window","description":"Denies the create_webview_window command without any pre-configured scope.","commands":{"allow":[],"deny":["create_webview_window"]},"scope":{}},"deny-internal-toggle-devtools":{"version":null,"identifier":"deny-internal-toggle-devtools","description":"Denies the internal_toggle_devtools command without any pre-configured scope.","commands":{"allow":[],"deny":["internal_toggle_devtools"]},"scope":{}},"deny-print":{"version":null,"identifier":"deny-print","description":"Denies the print command without any pre-configured scope.","commands":{"allow":[],"deny":["print"]},"scope":{}},"deny-set-webview-focus":{"version":null,"identifier":"deny-set-webview-focus","description":"Denies the set_webview_focus command without any pre-configured scope.","commands":{"allow":[],"deny":["set_webview_focus"]},"scope":{}},"deny-set-webview-position":{"version":null,"identifier":"deny-set-webview-position","description":"Denies the set_webview_position command without any pre-configured scope.","commands":{"allow":[],"deny":["set_webview_position"]},"scope":{}},"deny-set-webview-size":{"version":null,"identifier":"deny-set-webview-size","description":"Denies the set_webview_size command without any pre-configured scope.","commands":{"allow":[],"deny":["set_webview_size"]},"scope":{}},"deny-webview-close":{"version":null,"identifier":"deny-webview-close","description":"Denies the webview_close command without any pre-configured scope.","commands":{"allow":[],"deny":["webview_close"]},"scope":{}},"deny-webview-position":{"version":null,"identifier":"deny-webview-position","description":"Denies the webview_position command without any pre-configured scope.","commands":{"allow":[],"deny":["webview_position"]},"scope":{}},"deny-webview-size":{"version":null,"identifier":"deny-webview-size","description":"Denies the webview_size command without any pre-configured scope.","commands":{"allow":[],"deny":["webview_size"]},"scope":{}}},"permission_sets":{},"global_scope_schema":null},"window":{"default_permission":{"identifier":"default","description":"Default permissions for the plugin.","permissions":["allow-scale-factor","allow-inner-position","allow-outer-position","allow-inner-size","allow-outer-size","allow-is-fullscreen","allow-is-minimized","allow-is-maximized","allow-is-focused","allow-is-decorated","allow-is-resizable","allow-is-maximizable","allow-is-minimizable","allow-is-closable","allow-is-visible","allow-title","allow-current-monitor","allow-primary-monitor","allow-available-monitors","allow-theme","allow-internal-toggle-maximize","allow-internal-on-mousemove","allow-internal-on-mousedown"]},"permissions":{"allow-available-monitors":{"version":null,"identifier":"allow-available-monitors","description":"Enables the available_monitors command without any pre-configured scope.","commands":{"allow":["available_monitors"],"deny":[]},"scope":{}},"allow-center":{"version":null,"identifier":"allow-center","description":"Enables the center command without any pre-configured scope.","commands":{"allow":["center"],"deny":[]},"scope":{}},"allow-close":{"version":null,"identifier":"allow-close","description":"Enables the close command without any pre-configured scope.","commands":{"allow":["close"],"deny":[]},"scope":{}},"allow-create":{"version":null,"identifier":"allow-create","description":"Enables the create command without any pre-configured scope.","commands":{"allow":["create"],"deny":[]},"scope":{}},"allow-current-monitor":{"version":null,"identifier":"allow-current-monitor","description":"Enables the current_monitor command without any pre-configured scope.","commands":{"allow":["current_monitor"],"deny":[]},"scope":{}},"allow-destroy":{"version":null,"identifier":"allow-destroy","description":"Enables the destroy command without any pre-configured scope.","commands":{"allow":["destroy"],"deny":[]},"scope":{}},"allow-hide":{"version":null,"identifier":"allow-hide","description":"Enables the hide command without any pre-configured scope.","commands":{"allow":["hide"],"deny":[]},"scope":{}},"allow-inner-position":{"version":null,"identifier":"allow-inner-position","description":"Enables the inner_position command without any pre-configured scope.","commands":{"allow":["inner_position"],"deny":[]},"scope":{}},"allow-inner-size":{"version":null,"identifier":"allow-inner-size","description":"Enables the inner_size command without any pre-configured scope.","commands":{"allow":["inner_size"],"deny":[]},"scope":{}},"allow-internal-on-mousedown":{"version":null,"identifier":"allow-internal-on-mousedown","description":"Enables the internal_on_mousedown command without any pre-configured scope.","commands":{"allow":["internal_on_mousedown"],"deny":[]},"scope":{}},"allow-internal-on-mousemove":{"version":null,"identifier":"allow-internal-on-mousemove","description":"Enables the internal_on_mousemove command without any pre-configured scope.","commands":{"allow":["internal_on_mousemove"],"deny":[]},"scope":{}},"allow-internal-toggle-maximize":{"version":null,"identifier":"allow-internal-toggle-maximize","description":"Enables the internal_toggle_maximize command without any pre-configured scope.","commands":{"allow":["internal_toggle_maximize"],"deny":[]},"scope":{}},"allow-is-closable":{"version":null,"identifier":"allow-is-closable","description":"Enables the is_closable command without any pre-configured scope.","commands":{"allow":["is_closable"],"deny":[]},"scope":{}},"allow-is-decorated":{"version":null,"identifier":"allow-is-decorated","description":"Enables the is_decorated command without any pre-configured scope.","commands":{"allow":["is_decorated"],"deny":[]},"scope":{}},"allow-is-focused":{"version":null,"identifier":"allow-is-focused","description":"Enables the is_focused command without any pre-configured scope.","commands":{"allow":["is_focused"],"deny":[]},"scope":{}},"allow-is-fullscreen":{"version":null,"identifier":"allow-is-fullscreen","description":"Enables the is_fullscreen command without any pre-configured scope.","commands":{"allow":["is_fullscreen"],"deny":[]},"scope":{}},"allow-is-maximizable":{"version":null,"identifier":"allow-is-maximizable","description":"Enables the is_maximizable command without any pre-configured scope.","commands":{"allow":["is_maximizable"],"deny":[]},"scope":{}},"allow-is-maximized":{"version":null,"identifier":"allow-is-maximized","description":"Enables the is_maximized command without any pre-configured scope.","commands":{"allow":["is_maximized"],"deny":[]},"scope":{}},"allow-is-minimizable":{"version":null,"identifier":"allow-is-minimizable","description":"Enables the is_minimizable command without any pre-configured scope.","commands":{"allow":["is_minimizable"],"deny":[]},"scope":{}},"allow-is-minimized":{"version":null,"identifier":"allow-is-minimized","description":"Enables the is_minimized command without any pre-configured scope.","commands":{"allow":["is_minimized"],"deny":[]},"scope":{}},"allow-is-resizable":{"version":null,"identifier":"allow-is-resizable","description":"Enables the is_resizable command without any pre-configured scope.","commands":{"allow":["is_resizable"],"deny":[]},"scope":{}},"allow-is-visible":{"version":null,"identifier":"allow-is-visible","description":"Enables the is_visible command without any pre-configured scope.","commands":{"allow":["is_visible"],"deny":[]},"scope":{}},"allow-maximize":{"version":null,"identifier":"allow-maximize","description":"Enables the maximize command without any pre-configured scope.","commands":{"allow":["maximize"],"deny":[]},"scope":{}},"allow-minimize":{"version":null,"identifier":"allow-minimize","description":"Enables the minimize command without any pre-configured scope.","commands":{"allow":["minimize"],"deny":[]},"scope":{}},"allow-outer-position":{"version":null,"identifier":"allow-outer-position","description":"Enables the outer_position command without any pre-configured scope.","commands":{"allow":["outer_position"],"deny":[]},"scope":{}},"allow-outer-size":{"version":null,"identifier":"allow-outer-size","description":"Enables the outer_size command without any pre-configured scope.","commands":{"allow":["outer_size"],"deny":[]},"scope":{}},"allow-primary-monitor":{"version":null,"identifier":"allow-primary-monitor","description":"Enables the primary_monitor command without any pre-configured scope.","commands":{"allow":["primary_monitor"],"deny":[]},"scope":{}},"allow-request-user-attention":{"version":null,"identifier":"allow-request-user-attention","description":"Enables the request_user_attention command without any pre-configured scope.","commands":{"allow":["request_user_attention"],"deny":[]},"scope":{}},"allow-scale-factor":{"version":null,"identifier":"allow-scale-factor","description":"Enables the scale_factor command without any pre-configured scope.","commands":{"allow":["scale_factor"],"deny":[]},"scope":{}},"allow-set-always-on-bottom":{"version":null,"identifier":"allow-set-always-on-bottom","description":"Enables the set_always_on_bottom command without any pre-configured scope.","commands":{"allow":["set_always_on_bottom"],"deny":[]},"scope":{}},"allow-set-always-on-top":{"version":null,"identifier":"allow-set-always-on-top","description":"Enables the set_always_on_top command without any pre-configured scope.","commands":{"allow":["set_always_on_top"],"deny":[]},"scope":{}},"allow-set-closable":{"version":null,"identifier":"allow-set-closable","description":"Enables the set_closable command without any pre-configured scope.","commands":{"allow":["set_closable"],"deny":[]},"scope":{}},"allow-set-content-protected":{"version":null,"identifier":"allow-set-content-protected","description":"Enables the set_content_protected command without any pre-configured scope.","commands":{"allow":["set_content_protected"],"deny":[]},"scope":{}},"allow-set-cursor-grab":{"version":null,"identifier":"allow-set-cursor-grab","description":"Enables the set_cursor_grab command without any pre-configured scope.","commands":{"allow":["set_cursor_grab"],"deny":[]},"scope":{}},"allow-set-cursor-icon":{"version":null,"identifier":"allow-set-cursor-icon","description":"Enables the set_cursor_icon command without any pre-configured scope.","commands":{"allow":["set_cursor_icon"],"deny":[]},"scope":{}},"allow-set-cursor-position":{"version":null,"identifier":"allow-set-cursor-position","description":"Enables the set_cursor_position command without any pre-configured scope.","commands":{"allow":["set_cursor_position"],"deny":[]},"scope":{}},"allow-set-cursor-visible":{"version":null,"identifier":"allow-set-cursor-visible","description":"Enables the set_cursor_visible command without any pre-configured scope.","commands":{"allow":["set_cursor_visible"],"deny":[]},"scope":{}},"allow-set-decorations":{"version":null,"identifier":"allow-set-decorations","description":"Enables the set_decorations command without any pre-configured scope.","commands":{"allow":["set_decorations"],"deny":[]},"scope":{}},"allow-set-effects":{"version":null,"identifier":"allow-set-effects","description":"Enables the set_effects command without any pre-configured scope.","commands":{"allow":["set_effects"],"deny":[]},"scope":{}},"allow-set-focus":{"version":null,"identifier":"allow-set-focus","description":"Enables the set_focus command without any pre-configured scope.","commands":{"allow":["set_focus"],"deny":[]},"scope":{}},"allow-set-fullscreen":{"version":null,"identifier":"allow-set-fullscreen","description":"Enables the set_fullscreen command without any pre-configured scope.","commands":{"allow":["set_fullscreen"],"deny":[]},"scope":{}},"allow-set-icon":{"version":null,"identifier":"allow-set-icon","description":"Enables the set_icon command without any pre-configured scope.","commands":{"allow":["set_icon"],"deny":[]},"scope":{}},"allow-set-ignore-cursor-events":{"version":null,"identifier":"allow-set-ignore-cursor-events","description":"Enables the set_ignore_cursor_events command without any pre-configured scope.","commands":{"allow":["set_ignore_cursor_events"],"deny":[]},"scope":{}},"allow-set-max-size":{"version":null,"identifier":"allow-set-max-size","description":"Enables the set_max_size command without any pre-configured scope.","commands":{"allow":["set_max_size"],"deny":[]},"scope":{}},"allow-set-maximizable":{"version":null,"identifier":"allow-set-maximizable","description":"Enables the set_maximizable command without any pre-configured scope.","commands":{"allow":["set_maximizable"],"deny":[]},"scope":{}},"allow-set-min-size":{"version":null,"identifier":"allow-set-min-size","description":"Enables the set_min_size command without any pre-configured scope.","commands":{"allow":["set_min_size"],"deny":[]},"scope":{}},"allow-set-minimizable":{"version":null,"identifier":"allow-set-minimizable","description":"Enables the set_minimizable command without any pre-configured scope.","commands":{"allow":["set_minimizable"],"deny":[]},"scope":{}},"allow-set-position":{"version":null,"identifier":"allow-set-position","description":"Enables the set_position command without any pre-configured scope.","commands":{"allow":["set_position"],"deny":[]},"scope":{}},"allow-set-progress-bar":{"version":null,"identifier":"allow-set-progress-bar","description":"Enables the set_progress_bar command without any pre-configured scope.","commands":{"allow":["set_progress_bar"],"deny":[]},"scope":{}},"allow-set-resizable":{"version":null,"identifier":"allow-set-resizable","description":"Enables the set_resizable command without any pre-configured scope.","commands":{"allow":["set_resizable"],"deny":[]},"scope":{}},"allow-set-shadow":{"version":null,"identifier":"allow-set-shadow","description":"Enables the set_shadow command without any pre-configured scope.","commands":{"allow":["set_shadow"],"deny":[]},"scope":{}},"allow-set-size":{"version":null,"identifier":"allow-set-size","description":"Enables the set_size command without any pre-configured scope.","commands":{"allow":["set_size"],"deny":[]},"scope":{}},"allow-set-skip-taskbar":{"version":null,"identifier":"allow-set-skip-taskbar","description":"Enables the set_skip_taskbar command without any pre-configured scope.","commands":{"allow":["set_skip_taskbar"],"deny":[]},"scope":{}},"allow-set-title":{"version":null,"identifier":"allow-set-title","description":"Enables the set_title command without any pre-configured scope.","commands":{"allow":["set_title"],"deny":[]},"scope":{}},"allow-set-visible-on-all-workspaces":{"version":null,"identifier":"allow-set-visible-on-all-workspaces","description":"Enables the set_visible_on_all_workspaces command without any pre-configured scope.","commands":{"allow":["set_visible_on_all_workspaces"],"deny":[]},"scope":{}},"allow-show":{"version":null,"identifier":"allow-show","description":"Enables the show command without any pre-configured scope.","commands":{"allow":["show"],"deny":[]},"scope":{}},"allow-start-dragging":{"version":null,"identifier":"allow-start-dragging","description":"Enables the start_dragging command without any pre-configured scope.","commands":{"allow":["start_dragging"],"deny":[]},"scope":{}},"allow-theme":{"version":null,"identifier":"allow-theme","description":"Enables the theme command without any pre-configured scope.","commands":{"allow":["theme"],"deny":[]},"scope":{}},"allow-title":{"version":null,"identifier":"allow-title","description":"Enables the title command without any pre-configured scope.","commands":{"allow":["title"],"deny":[]},"scope":{}},"allow-toggle-maximize":{"version":null,"identifier":"allow-toggle-maximize","description":"Enables the toggle_maximize command without any pre-configured scope.","commands":{"allow":["toggle_maximize"],"deny":[]},"scope":{}},"allow-unmaximize":{"version":null,"identifier":"allow-unmaximize","description":"Enables the unmaximize command without any pre-configured scope.","commands":{"allow":["unmaximize"],"deny":[]},"scope":{}},"allow-unminimize":{"version":null,"identifier":"allow-unminimize","description":"Enables the unminimize command without any pre-configured scope.","commands":{"allow":["unminimize"],"deny":[]},"scope":{}},"deny-available-monitors":{"version":null,"identifier":"deny-available-monitors","description":"Denies the available_monitors command without any pre-configured scope.","commands":{"allow":[],"deny":["available_monitors"]},"scope":{}},"deny-center":{"version":null,"identifier":"deny-center","description":"Denies the center command without any pre-configured scope.","commands":{"allow":[],"deny":["center"]},"scope":{}},"deny-close":{"version":null,"identifier":"deny-close","description":"Denies the close command without any pre-configured scope.","commands":{"allow":[],"deny":["close"]},"scope":{}},"deny-create":{"version":null,"identifier":"deny-create","description":"Denies the create command without any pre-configured scope.","commands":{"allow":[],"deny":["create"]},"scope":{}},"deny-current-monitor":{"version":null,"identifier":"deny-current-monitor","description":"Denies the current_monitor command without any pre-configured scope.","commands":{"allow":[],"deny":["current_monitor"]},"scope":{}},"deny-destroy":{"version":null,"identifier":"deny-destroy","description":"Denies the destroy command without any pre-configured scope.","commands":{"allow":[],"deny":["destroy"]},"scope":{}},"deny-hide":{"version":null,"identifier":"deny-hide","description":"Denies the hide command without any pre-configured scope.","commands":{"allow":[],"deny":["hide"]},"scope":{}},"deny-inner-position":{"version":null,"identifier":"deny-inner-position","description":"Denies the inner_position command without any pre-configured scope.","commands":{"allow":[],"deny":["inner_position"]},"scope":{}},"deny-inner-size":{"version":null,"identifier":"deny-inner-size","description":"Denies the inner_size command without any pre-configured scope.","commands":{"allow":[],"deny":["inner_size"]},"scope":{}},"deny-internal-on-mousedown":{"version":null,"identifier":"deny-internal-on-mousedown","description":"Denies the internal_on_mousedown command without any pre-configured scope.","commands":{"allow":[],"deny":["internal_on_mousedown"]},"scope":{}},"deny-internal-on-mousemove":{"version":null,"identifier":"deny-internal-on-mousemove","description":"Denies the internal_on_mousemove command without any pre-configured scope.","commands":{"allow":[],"deny":["internal_on_mousemove"]},"scope":{}},"deny-internal-toggle-maximize":{"version":null,"identifier":"deny-internal-toggle-maximize","description":"Denies the internal_toggle_maximize command without any pre-configured scope.","commands":{"allow":[],"deny":["internal_toggle_maximize"]},"scope":{}},"deny-is-closable":{"version":null,"identifier":"deny-is-closable","description":"Denies the is_closable command without any pre-configured scope.","commands":{"allow":[],"deny":["is_closable"]},"scope":{}},"deny-is-decorated":{"version":null,"identifier":"deny-is-decorated","description":"Denies the is_decorated command without any pre-configured scope.","commands":{"allow":[],"deny":["is_decorated"]},"scope":{}},"deny-is-focused":{"version":null,"identifier":"deny-is-focused","description":"Denies the is_focused command without any pre-configured scope.","commands":{"allow":[],"deny":["is_focused"]},"scope":{}},"deny-is-fullscreen":{"version":null,"identifier":"deny-is-fullscreen","description":"Denies the is_fullscreen command without any pre-configured scope.","commands":{"allow":[],"deny":["is_fullscreen"]},"scope":{}},"deny-is-maximizable":{"version":null,"identifier":"deny-is-maximizable","description":"Denies the is_maximizable command without any pre-configured scope.","commands":{"allow":[],"deny":["is_maximizable"]},"scope":{}},"deny-is-maximized":{"version":null,"identifier":"deny-is-maximized","description":"Denies the is_maximized command without any pre-configured scope.","commands":{"allow":[],"deny":["is_maximized"]},"scope":{}},"deny-is-minimizable":{"version":null,"identifier":"deny-is-minimizable","description":"Denies the is_minimizable command without any pre-configured scope.","commands":{"allow":[],"deny":["is_minimizable"]},"scope":{}},"deny-is-minimized":{"version":null,"identifier":"deny-is-minimized","description":"Denies the is_minimized command without any pre-configured scope.","commands":{"allow":[],"deny":["is_minimized"]},"scope":{}},"deny-is-resizable":{"version":null,"identifier":"deny-is-resizable","description":"Denies the is_resizable command without any pre-configured scope.","commands":{"allow":[],"deny":["is_resizable"]},"scope":{}},"deny-is-visible":{"version":null,"identifier":"deny-is-visible","description":"Denies the is_visible command without any pre-configured scope.","commands":{"allow":[],"deny":["is_visible"]},"scope":{}},"deny-maximize":{"version":null,"identifier":"deny-maximize","description":"Denies the maximize command without any pre-configured scope.","commands":{"allow":[],"deny":["maximize"]},"scope":{}},"deny-minimize":{"version":null,"identifier":"deny-minimize","description":"Denies the minimize command without any pre-configured scope.","commands":{"allow":[],"deny":["minimize"]},"scope":{}},"deny-outer-position":{"version":null,"identifier":"deny-outer-position","description":"Denies the outer_position command without any pre-configured scope.","commands":{"allow":[],"deny":["outer_position"]},"scope":{}},"deny-outer-size":{"version":null,"identifier":"deny-outer-size","description":"Denies the outer_size command without any pre-configured scope.","commands":{"allow":[],"deny":["outer_size"]},"scope":{}},"deny-primary-monitor":{"version":null,"identifier":"deny-primary-monitor","description":"Denies the primary_monitor command without any pre-configured scope.","commands":{"allow":[],"deny":["primary_monitor"]},"scope":{}},"deny-request-user-attention":{"version":null,"identifier":"deny-request-user-attention","description":"Denies the request_user_attention command without any pre-configured scope.","commands":{"allow":[],"deny":["request_user_attention"]},"scope":{}},"deny-scale-factor":{"version":null,"identifier":"deny-scale-factor","description":"Denies the scale_factor command without any pre-configured scope.","commands":{"allow":[],"deny":["scale_factor"]},"scope":{}},"deny-set-always-on-bottom":{"version":null,"identifier":"deny-set-always-on-bottom","description":"Denies the set_always_on_bottom command without any pre-configured scope.","commands":{"allow":[],"deny":["set_always_on_bottom"]},"scope":{}},"deny-set-always-on-top":{"version":null,"identifier":"deny-set-always-on-top","description":"Denies the set_always_on_top command without any pre-configured scope.","commands":{"allow":[],"deny":["set_always_on_top"]},"scope":{}},"deny-set-closable":{"version":null,"identifier":"deny-set-closable","description":"Denies the set_closable command without any pre-configured scope.","commands":{"allow":[],"deny":["set_closable"]},"scope":{}},"deny-set-content-protected":{"version":null,"identifier":"deny-set-content-protected","description":"Denies the set_content_protected command without any pre-configured scope.","commands":{"allow":[],"deny":["set_content_protected"]},"scope":{}},"deny-set-cursor-grab":{"version":null,"identifier":"deny-set-cursor-grab","description":"Denies the set_cursor_grab command without any pre-configured scope.","commands":{"allow":[],"deny":["set_cursor_grab"]},"scope":{}},"deny-set-cursor-icon":{"version":null,"identifier":"deny-set-cursor-icon","description":"Denies the set_cursor_icon command without any pre-configured scope.","commands":{"allow":[],"deny":["set_cursor_icon"]},"scope":{}},"deny-set-cursor-position":{"version":null,"identifier":"deny-set-cursor-position","description":"Denies the set_cursor_position command without any pre-configured scope.","commands":{"allow":[],"deny":["set_cursor_position"]},"scope":{}},"deny-set-cursor-visible":{"version":null,"identifier":"deny-set-cursor-visible","description":"Denies the set_cursor_visible command without any pre-configured scope.","commands":{"allow":[],"deny":["set_cursor_visible"]},"scope":{}},"deny-set-decorations":{"version":null,"identifier":"deny-set-decorations","description":"Denies the set_decorations command without any pre-configured scope.","commands":{"allow":[],"deny":["set_decorations"]},"scope":{}},"deny-set-effects":{"version":null,"identifier":"deny-set-effects","description":"Denies the set_effects command without any pre-configured scope.","commands":{"allow":[],"deny":["set_effects"]},"scope":{}},"deny-set-focus":{"version":null,"identifier":"deny-set-focus","description":"Denies the set_focus command without any pre-configured scope.","commands":{"allow":[],"deny":["set_focus"]},"scope":{}},"deny-set-fullscreen":{"version":null,"identifier":"deny-set-fullscreen","description":"Denies the set_fullscreen command without any pre-configured scope.","commands":{"allow":[],"deny":["set_fullscreen"]},"scope":{}},"deny-set-icon":{"version":null,"identifier":"deny-set-icon","description":"Denies the set_icon command without any pre-configured scope.","commands":{"allow":[],"deny":["set_icon"]},"scope":{}},"deny-set-ignore-cursor-events":{"version":null,"identifier":"deny-set-ignore-cursor-events","description":"Denies the set_ignore_cursor_events command without any pre-configured scope.","commands":{"allow":[],"deny":["set_ignore_cursor_events"]},"scope":{}},"deny-set-max-size":{"version":null,"identifier":"deny-set-max-size","description":"Denies the set_max_size command without any pre-configured scope.","commands":{"allow":[],"deny":["set_max_size"]},"scope":{}},"deny-set-maximizable":{"version":null,"identifier":"deny-set-maximizable","description":"Denies the set_maximizable command without any pre-configured scope.","commands":{"allow":[],"deny":["set_maximizable"]},"scope":{}},"deny-set-min-size":{"version":null,"identifier":"deny-set-min-size","description":"Denies the set_min_size command without any pre-configured scope.","commands":{"allow":[],"deny":["set_min_size"]},"scope":{}},"deny-set-minimizable":{"version":null,"identifier":"deny-set-minimizable","description":"Denies the set_minimizable command without any pre-configured scope.","commands":{"allow":[],"deny":["set_minimizable"]},"scope":{}},"deny-set-position":{"version":null,"identifier":"deny-set-position","description":"Denies the set_position command without any pre-configured scope.","commands":{"allow":[],"deny":["set_position"]},"scope":{}},"deny-set-progress-bar":{"version":null,"identifier":"deny-set-progress-bar","description":"Denies the set_progress_bar command without any pre-configured scope.","commands":{"allow":[],"deny":["set_progress_bar"]},"scope":{}},"deny-set-resizable":{"version":null,"identifier":"deny-set-resizable","description":"Denies the set_resizable command without any pre-configured scope.","commands":{"allow":[],"deny":["set_resizable"]},"scope":{}},"deny-set-shadow":{"version":null,"identifier":"deny-set-shadow","description":"Denies the set_shadow command without any pre-configured scope.","commands":{"allow":[],"deny":["set_shadow"]},"scope":{}},"deny-set-size":{"version":null,"identifier":"deny-set-size","description":"Denies the set_size command without any pre-configured scope.","commands":{"allow":[],"deny":["set_size"]},"scope":{}},"deny-set-skip-taskbar":{"version":null,"identifier":"deny-set-skip-taskbar","description":"Denies the set_skip_taskbar command without any pre-configured scope.","commands":{"allow":[],"deny":["set_skip_taskbar"]},"scope":{}},"deny-set-title":{"version":null,"identifier":"deny-set-title","description":"Denies the set_title command without any pre-configured scope.","commands":{"allow":[],"deny":["set_title"]},"scope":{}},"deny-set-visible-on-all-workspaces":{"version":null,"identifier":"deny-set-visible-on-all-workspaces","description":"Denies the set_visible_on_all_workspaces command without any pre-configured scope.","commands":{"allow":[],"deny":["set_visible_on_all_workspaces"]},"scope":{}},"deny-show":{"version":null,"identifier":"deny-show","description":"Denies the show command without any pre-configured scope.","commands":{"allow":[],"deny":["show"]},"scope":{}},"deny-start-dragging":{"version":null,"identifier":"deny-start-dragging","description":"Denies the start_dragging command without any pre-configured scope.","commands":{"allow":[],"deny":["start_dragging"]},"scope":{}},"deny-theme":{"version":null,"identifier":"deny-theme","description":"Denies the theme command without any pre-configured scope.","commands":{"allow":[],"deny":["theme"]},"scope":{}},"deny-title":{"version":null,"identifier":"deny-title","description":"Denies the title command without any pre-configured scope.","commands":{"allow":[],"deny":["title"]},"scope":{}},"deny-toggle-maximize":{"version":null,"identifier":"deny-toggle-maximize","description":"Denies the toggle_maximize command without any pre-configured scope.","commands":{"allow":[],"deny":["toggle_maximize"]},"scope":{}},"deny-unmaximize":{"version":null,"identifier":"deny-unmaximize","description":"Denies the unmaximize command without any pre-configured scope.","commands":{"allow":[],"deny":["unmaximize"]},"scope":{}},"deny-unminimize":{"version":null,"identifier":"deny-unminimize","description":"Denies the unminimize command without any pre-configured scope.","commands":{"allow":[],"deny":["unminimize"]},"scope":{}}},"permission_sets":{},"global_scope_schema":null}}